getai/__init__.py
getai/__main__.py
getai/api/__init__.py
getai/api/datasets.py
getai/api/models.py
getai/api/utils.py
getai/cli/__init__.py
getai/cli/cli.py
getai/cli/utils.py
getai/core/__init__.py
getai/core/dataset_downloader.py
getai/core/dataset_search.py
getai/core/model_downloader.py
getai/core/model_search.py
getai/core/session_manager.py
getai/core/utils.py
getai/examples/example_getai_stanfordnlp_imdb_dataset.py
getai/tests/__init__.py
getai/tests/init_test.py
getai/tests/test__main__.py
getai/tests/test_api.py
getai/tests/test_cli.py
getai/tests/test_core.py
getai/tests/test_import_issues.py
getai/tests/test_init_.py
getai/tests/test_main.py
getai/tests/test_main_cli.py
getai/tests/test_script_execution.py
getai/tests/test_utils.py
getai-0.0.986.dist-info/LICENSE
getai-0.0.986.dist-info/METADATA
getai-0.0.986.dist-info/WHEEL
getai-0.0.986.dist-info/entry_points.txt
getai-0.0.986.dist-info/RECORD
