Metadata-Version: 2.1
Name: getai
Version: 0.0.986
Summary: GetAI - An asynchronous AI search and download tool for AI models, datasets, and tools. Designed to streamline the process of downloading machine learning models, datasets, and more.
License: MIT - with attribution
Author: Ben Gorlick
Author-email: ben@unifiedlearning.ai
Requires-Python: >=3.9,<4.0
Classifier: License :: Other/Proprietary License
Classifier: Programming Language :: Python :: 3
Classifier: Programming Language :: Python :: 3.9
Classifier: Programming Language :: Python :: 3.10
Classifier: Programming Language :: Python :: 3.11
Classifier: Programming Language :: Python :: 3.12
Requires-Dist: aiofiles (>=23.2.1,<24.0.0)
Requires-Dist: aiohttp (>=3.9.3,<4.0.0)
Requires-Dist: prompt-toolkit (>=3.0.43,<4.0.0)
Requires-Dist: rainbow-tqdm (>=0.1.5,<0.2.0)
Requires-Dist: tenacity (>=8.0.1,<9.0.0)
Requires-Dist: types-aiofiles (>=0.1.0,<0.2.0)
